img_merge/__init__.py
img_merge/merge.py
img_merge-1.2.dist-info/METADATA
img_merge-1.2.dist-info/WHEEL
img_merge-1.2.dist-info/top_level.txt
img_merge-1.2.dist-info/RECORD
